README.md
setup.py
ggpay/__init__.py
ggpay/ggpay.py
ggpay/token_helper.py
ggpay.egg-info/PKG-INFO
ggpay.egg-info/SOURCES.txt
ggpay.egg-info/dependency_links.txt
ggpay.egg-info/requires.txt
ggpay.egg-info/top_level.txt