Metadata-Version: 1.0
Name: ggpay
Version: 0.3.1
Summary: google支付订单验证
Home-page: https://github.com/dantezhu/ggpay
Author: dantezhu
Author-email: dantezhu@qq.com
License: MIT
Platform: UNKNOWN
